spiderbot/__init__.py
spiderbot/bot.py
spiderbot/config_private.py
spiderbot/config_private_sample.py
spiderbot/models/__init__.py
spiderbot/models/api.py
spiderbot/models/base.py
spiderbot/models/posts.py
spiderbot/models/posturls.py
spiderbot/models/temp.api.py
spiderbot/models/users.py
spiderbot-0.3.3.dist-info/LICENSE
spiderbot-0.3.3.dist-info/METADATA
spiderbot-0.3.3.dist-info/WHEEL
spiderbot-0.3.3.dist-info/top_level.txt
spiderbot-0.3.3.dist-info/RECORD
