Metadata-Version: 2.1
Name: spiderbot
Version: 0.3.3
Summary: a spider bot (scrawler) by python, using selenium and chrome driver
Home-page: https://github.com/liujuanjuan1984/spiderbot
Author: liujuanjuan1984
Author-email: qiaoanlu@163.com
Project-URL: Github Repo, https://github.com/liujuanjuan1984/spiderbot
Project-URL: Bug Tracker, https://github.com/liujuanjuan1984/spiderbot/issues
Keywords: selenium,spider,chrome,bot,scrawler
Classifier: Programming Language :: Python :: 3
Classifier: Programming Language :: Python :: 3.9
Classifier: License :: OSI Approved :: GNU General Public License v3 (GPLv3)
Classifier: Operating System :: OS Independent
Requires-Python: >=3.5
License-File: LICENSE
Requires-Dist: selenium
